dp_xgboost-0.2.10.dist-info/WHEEL
dp_xgboost-0.2.10.dist-info/RECORD
dp_xgboost-0.2.10.dist-info/top_level.txt
dp_xgboost-0.2.10.dist-info/METADATA
dp_xgboost/core.py
dp_xgboost/sklearn.py
dp_xgboost/VERSION
dp_xgboost/dask.py
dp_xgboost/compat.py
dp_xgboost/callback.py
dp_xgboost/plotting.py
dp_xgboost/__init__.py
dp_xgboost/tracker.py
dp_xgboost/rabit.py
dp_xgboost/data.py
dp_xgboost/libpath.py
dp_xgboost/config.py
dp_xgboost/training.py
dp_xgboost/py.typed
dp_xgboost/lib/libxgboost.so
