Metadata-Version: 2.1
Name: dp-xgboost
Version: 0.2.10
Summary: DP-XGBoost Python Package from Sarus
Home-page: https://github.com/sarus-tech/dp-xgboost
Maintainer: Nicolas Grislain
Maintainer-email: ng@sarus.tech
License: Apache-2.0
Classifier: License :: OSI Approved :: Apache Software License
Classifier: Development Status :: 5 - Production/Stable
Classifier: Operating System :: OS Independent
Classifier: Programming Language :: Python
Classifier: Programming Language :: Python :: 3
Classifier: Programming Language :: Python :: 3.6
Classifier: Programming Language :: Python :: 3.7
Classifier: Programming Language :: Python :: 3.8
Requires-Python: >=3.6
Requires-Dist: numpy
Requires-Dist: scipy
Provides-Extra: dask
Requires-Dist: dask ; extra == 'dask'
Requires-Dist: pandas ; extra == 'dask'
Requires-Dist: distributed ; extra == 'dask'
Provides-Extra: datatable
Requires-Dist: datatable ; extra == 'datatable'
Provides-Extra: pandas
Requires-Dist: pandas ; extra == 'pandas'
Provides-Extra: plotting
Requires-Dist: graphviz ; extra == 'plotting'
Requires-Dist: matplotlib ; extra == 'plotting'
Provides-Extra: scikit-learn
Requires-Dist: scikit-learn ; extra == 'scikit-learn'
